README.txt
setup.py
mailchimp/__init__.py
mailchimp/api.py
mailchimp/tests.py
python_mailchimp.egg-info/PKG-INFO
python_mailchimp.egg-info/SOURCES.txt
python_mailchimp.egg-info/dependency_links.txt
python_mailchimp.egg-info/requires.txt
python_mailchimp.egg-info/top_level.txt
python_mailchimp.egg-info/zip-safe