Metadata-Version: 1.1
Name: python-mailchimp
Version: 1.0
Summary: MailChimp API v1.3 wrapper for Python.
Home-page: https://github.com/eugene-wee/python-mailchimp
Author: John-Kim Murphy, Eugene Wee
Author-email: UNKNOWN
License: UNKNOWN
Download-URL: https://github.com/eugene-wee/python-mailchimp/tarball/master
Keywords: mailchimp api wrapper 1.3
Platform: UNKNOWN
Classifier: Development Status :: 5 - Production/Stable
Classifier: Intended Audience :: Developers
Classifier: License :: OSI Approved :: MIT License
Classifier: Natural Language :: English
Classifier: Operating System :: OS Independent
Classifier: Programming Language :: Python
Classifier: Topic :: Software Development :: Libraries :: Python Modules
